Metadata-Version: 2.1
Name: rays-pycocotools
Version: 2.6.5
Summary: Wrapper of pycocotools that correctly installs with pip.
Requires-Python: >=3.6
Provides-Extra: all
